babish_db-0.0.1.data/scripts/ibdb
ibdb/__init__.py
ibdb/__main__.py
ibdb/api.py
ibdb/cli.py
ibdb/export.py
ibdb/extract.py
ibdb/extract_recipes.py
ibdb/models.py
ibdb/populate_babish_json.py
ibdb/populate_db.py
ibdb/recipe_parser.py
ibdb/settings.py
ibdb/sync.py
ibdb/utils.py
ibdb/routes/__init__.py
ibdb/routes/base/__init__.py
ibdb/routes/base/base.py
ibdb/routes/episode/__init__.py
ibdb/routes/episode/episode.py
ibdb/routes/guest/__init__.py
ibdb/routes/guest/guest.py
ibdb/routes/recipe/__init__.py
ibdb/routes/recipe/recipe.py
ibdb/routes/reference/__init__.py
ibdb/routes/reference/reference.py
ibdb/routes/show/__init__.py
ibdb/routes/show/show.py
vendor/__init__.py
vendor/pg_dump_splitsort.py
babish_db-0.0.1.dist-info/LICENSE
babish_db-0.0.1.dist-info/METADATA
babish_db-0.0.1.dist-info/WHEEL
babish_db-0.0.1.dist-info/top_level.txt
babish_db-0.0.1.dist-info/RECORD
