Metadata-Version: 2.1
Name: babish-db
Version: 0.0.1
Summary: Data with Babish DB
Home-page: https://github.com/jklewa/data-with-babish
Author: jklewa
Author-email: jklewa@gmail.com
License: GPLv3+
Platform: UNKNOWN
Classifier: Programming Language :: Python :: 3
Classifier: License :: OSI Approved :: GNU General Public License v3 or later (GPLv3+)
Classifier: Operating System :: OS Independent
Requires-Python: >=3.6
Requires-Dist: beautifulsoup4
Requires-Dist: click
Requires-Dist: flask
Requires-Dist: flask-migrate
Requires-Dist: flask-sqlalchemy
Requires-Dist: furl
Requires-Dist: html5lib
Requires-Dist: measurement
Requires-Dist: psycopg2-binary
Requires-Dist: pyfunctional
Requires-Dist: requests
